{
  "modelVersion" : "2.2",
  "previousArtifactVersion" : "2.0",
  "id" : "SuccessResponsePopUp",
  "name" : "SuccessResponsePopUp",
  "lastUpdate" : 1671627915458,
  "rows" : [
    [
      {
        "type" : "container",
        "dimension" : {
          "xs" : 12,
          "sm" : 12,
          "md" : 4,
          "lg" : 4
        },
        "propertyValues" : {
          "cssClasses" : {
            "type" : "constant",
            "value" : ""
          },
          "hidden" : {
            "type" : "constant",
            "value" : false
          },
          "repeatedCollection" : {
            "type" : "variable"
          }
        },
        "reference" : "b21c9fea-cac5-44cf-a51b-aaa25006a28c",
        "hasValidationError" : false,
        "id" : "pbContainer",
        "rows" : [
          [ ]
        ]
      },
      {
        "type" : "container",
        "dimension" : {
          "xs" : 12,
          "sm" : 12,
          "md" : 4,
          "lg" : 4
        },
        "propertyValues" : {
          "cssClasses" : {
            "type" : "constant",
            "value" : "Modal-overlay"
          },
          "hidden" : {
            "type" : "constant",
            "value" : false
          },
          "repeatedCollection" : {
            "type" : "variable"
          }
        },
        "reference" : "b4cd3357-802f-4d12-b8ed-94eacf292594",
        "hasValidationError" : false,
        "id" : "pbContainer",
        "rows" : [
          [
            {
              "type" : "container",
              "dimension" : {
                "xs" : 12,
                "sm" : 12,
                "md" : 12,
                "lg" : 12
              },
              "propertyValues" : {
                "cssClasses" : {
                  "type" : "constant",
                  "value" : "Modal-content"
                },
                "hidden" : {
                  "type" : "constant",
                  "value" : false
                },
                "repeatedCollection" : {
                  "type" : "variable",
                  "value" : ""
                }
              },
              "reference" : "9e7a8856-cf5c-4971-a4e4-f1f389e1f03a",
              "hasValidationError" : false,
              "id" : "pbContainer",
              "rows" : [
                [
                  {
                    "type" : "component",
                    "dimension" : {
                      "xs" : 12,
                      "sm" : 12,
                      "md" : 12,
                      "lg" : 12
                    },
                    "propertyValues" : {
                      "cssClasses" : {
                        "type" : "constant",
                        "value" : "alert alert-warning"
                      },
                      "hidden" : {
                        "type" : "constant",
                        "value" : false
                      },
                      "text" : {
                        "type" : "interpolation",
                        "value" : ""
                      },
                      "level" : {
                        "type" : "constant",
                        "value" : "Level 4"
                      },
                      "alignment" : {
                        "type" : "constant",
                        "value" : "left"
                      }
                    },
                    "reference" : "bc97e13f-14c0-4725-9a75-d5e1465beee6",
                    "hasValidationError" : false,
                    "id" : "pbTitle"
                  }
                ],
                [
                  {
                    "type" : "container",
                    "dimension" : {
                      "xs" : 12,
                      "sm" : 12,
                      "md" : 12,
                      "lg" : 12
                    },
                    "propertyValues" : {
                      "cssClasses" : {
                        "type" : "constant",
                        "value" : ""
                      },
                      "hidden" : {
                        "type" : "constant",
                        "value" : false
                      },
                      "repeatedCollection" : {
                        "type" : "variable",
                        "value" : ""
                      }
                    },
                    "reference" : "8027bfb3-8e67-4089-a8b3-9e61083ddce4",
                    "hasValidationError" : false,
                    "id" : "pbContainer",
                    "rows" : [
                      [
                        {
                          "type" : "component",
                          "dimension" : {
                            "xs" : 12,
                            "sm" : 12,
                            "md" : 12,
                            "lg" : 12
                          },
                          "propertyValues" : {
                            "cssClasses" : {
                              "type" : "constant",
                              "value" : ""
                            },
                            "hidden" : {
                              "type" : "constant",
                              "value" : false
                            },
                            "text" : {
                              "type" : "interpolation",
                              "value" : "{{ displayPopupTypeAcquisitionMessage }}"
                            },
                            "alignment" : {
                              "type" : "constant",
                              "value" : "left"
                            },
                            "allowHTML" : {
                              "type" : "constant",
                              "value" : true
                            },
                            "labelHidden" : {
                              "type" : "constant",
                              "value" : true
                            },
                            "label" : {
                              "type" : "interpolation",
                              "value" : ""
                            },
                            "labelPosition" : {
                              "type" : "constant",
                              "value" : "top"
                            },
                            "labelWidth" : {
                              "type" : "constant",
                              "value" : 4
                            }
                          },
                          "reference" : "4b0211f2-a255-49f6-84c1-6c0b563d1732",
                          "hasValidationError" : false,
                          "id" : "pbText"
                        }
                      ],
                      [
                        {
                          "type" : "component",
                          "dimension" : {
                            "xs" : 12,
                            "sm" : 12,
                            "md" : 12,
                            "lg" : 6
                          },
                          "propertyValues" : {
                            "cssClasses" : {
                              "type" : "constant",
                              "value" : ""
                            },
                            "hidden" : {
                              "type" : "constant",
                              "value" : false
                            },
                            "disabled" : {
                              "type" : "constant",
                              "value" : false
                            },
                            "label" : {
                              "type" : "interpolation",
                              "value" : "OK"
                            },
                            "alignment" : {
                              "type" : "constant",
                              "value" : "center"
                            },
                            "buttonStyle" : {
                              "type" : "constant",
                              "value" : "primary"
                            },
                            "action" : {
                              "type" : "constant",
                              "value" : "Submit task"
                            },
                            "url" : {
                              "type" : "interpolation"
                            },
                            "dataToSend" : {
                              "type" : "constant"
                            },
                            "dataFromSuccess" : {
                              "type" : "variable",
                              "value" : ""
                            },
                            "dataFromError" : {
                              "type" : "variable",
                              "value" : "errorMessage"
                            },
                            "targetUrlOnSuccess" : {
                              "type" : "interpolation",
                              "value" : "/bonita/apps/Rejouertimelines"
                            },
                            "collectionToModify" : {
                              "type" : "variable"
                            },
                            "collectionPosition" : {
                              "type" : "constant",
                              "value" : "Last"
                            },
                            "valueToAdd" : {
                              "type" : "constant"
                            },
                            "removeItem" : {
                              "type" : "variable"
                            },
                            "assign" : {
                              "type" : "constant",
                              "value" : false
                            },
                            "responseStatusCode" : {
                              "type" : "variable",
                              "value" : ""
                            },
                            "closeOnSuccess" : {
                              "type" : "constant",
                              "value" : false
                            },
                            "modalId" : {
                              "type" : "constant",
                              "value" : ""
                            }
                          },
                          "reference" : "35dcb5f8-9c6c-4bf3-9571-f5cf33c55a35",
                          "hasValidationError" : false,
                          "id" : "pbButton"
                        }
                      ]
                    ]
                  }
                ]
              ]
            }
          ]
        ]
      }
    ]
  ],
  "assets" : [ ],
  "inactiveAssets" : [ ],
  "variables" : {
    "propositionData" : {
      "type" : "constant",
      "value" : [
        ""
      ],
      "exposed" : true
    },
    "ifErrorMessage" : {
      "type" : "expression",
      "value" : [
        "",
        "",
        "if($data.errorMessage && $data.errorMessage != {}){",
        "    $data.propositionData.pop();",
        "}"
      ],
      "exposed" : false
    },
    "displayPopupTypeAcquisitionMessage" : {
      "type" : "expression",
      "value" : [
        "return \"Timeline rejouées avec succès\";"
      ],
      "exposed" : false
    },
    "formOutput" : {
      "type" : "constant",
      "value" : [
        ""
      ],
      "exposed" : true
    },
    "typeWorkflow" : {
      "type" : "constant",
      "value" : [
        ""
      ],
      "exposed" : true
    },
    "errorMessage" : {
      "type" : "constant",
      "value" : [
        ""
      ],
      "exposed" : true
    },
    "targetURLOnSuccess" : {
      "type" : "expression",
      "value" : [
        "// Switch when the use is on the SAV or the SMARTE",
        "// The \"Get url and look in witch app you are\" does not work",
        "// because the dorm is in a iframe ",
        "// -> Add the typeWorkflow to choose the URL",
        "",
        "var targetURLOnSuccess = \"\";",
        "if ($data.typeWorkflow === \"DADR\") {",
        "    targetURLOnSuccess = \"/bonita/apps/SAV/\";",
        "} else {",
        "    targetURLOnSuccess = \"/bonita/apps/pop3p/\";",
        "}",
        "",
        "return targetURLOnSuccess;"
      ],
      "exposed" : false
    }
  },
  "hasValidationError" : false,
  "type" : "fragment"
}