{
  "modelVersion" : "2.2",
  "previousArtifactVersion" : "2.0",
  "id" : "96c97b6b-8578-47f5-8914-3378a66d6b1d",
  "name" : "POCColorBackground",
  "lastUpdate" : 1671627896737,
  "rows" : [
    [
      {
        "type" : "container",
        "dimension" : {
          "xs" : 12,
          "sm" : 12,
          "md" : 12,
          "lg" : 12
        },
        "propertyValues" : {
          "cssClasses" : {
            "type" : "constant",
            "value" : ""
          },
          "hidden" : {
            "type" : "constant",
            "value" : false
          },
          "repeatedCollection" : {
            "type" : "variable"
          }
        },
        "reference" : "6ddd4ed8-15a9-441e-b432-34c6c740f5cd",
        "hasValidationError" : false,
        "id" : "pbContainer",
        "rows" : [
          [
            {
              "type" : "component",
              "dimension" : {
                "xs" : 12,
                "sm" : 12,
                "md" : 2,
                "lg" : 2
              },
              "propertyValues" : {
                "cssClasses" : {
                  "type" : "constant",
                  "value" : ""
                },
                "hidden" : {
                  "type" : "constant",
                  "value" : false
                },
                "text" : {
                  "type" : "interpolation",
                  "value" : "<b> codeNoeudApprob</b>"
                },
                "alignment" : {
                  "type" : "constant",
                  "value" : "left"
                },
                "allowHTML" : {
                  "type" : "constant",
                  "value" : true
                },
                "labelHidden" : {
                  "type" : "constant",
                  "value" : true
                },
                "label" : {
                  "type" : "interpolation",
                  "value" : ""
                },
                "labelPosition" : {
                  "type" : "constant",
                  "value" : "top"
                },
                "labelWidth" : {
                  "type" : "constant",
                  "value" : 4
                }
              },
              "reference" : "0c1c58b9-b2a9-4b08-93b7-a7b78ed97725",
              "hasValidationError" : false,
              "id" : "pbText"
            },
            {
              "type" : "component",
              "dimension" : {
                "xs" : 12,
                "sm" : 12,
                "md" : 2,
                "lg" : 2
              },
              "propertyValues" : {
                "cssClasses" : {
                  "type" : "constant",
                  "value" : ""
                },
                "hidden" : {
                  "type" : "constant",
                  "value" : false
                },
                "text" : {
                  "type" : "interpolation",
                  "value" : "<b> nomNoeudApprob </b>"
                },
                "alignment" : {
                  "type" : "constant",
                  "value" : "left"
                },
                "allowHTML" : {
                  "type" : "constant",
                  "value" : true
                },
                "labelHidden" : {
                  "type" : "constant",
                  "value" : true
                },
                "label" : {
                  "type" : "interpolation",
                  "value" : ""
                },
                "labelPosition" : {
                  "type" : "constant",
                  "value" : "top"
                },
                "labelWidth" : {
                  "type" : "constant",
                  "value" : 4
                }
              },
              "reference" : "4b33ee8e-47d1-4215-9b44-16099592237f",
              "hasValidationError" : false,
              "id" : "pbText"
            },
            {
              "type" : "component",
              "dimension" : {
                "xs" : 12,
                "sm" : 12,
                "md" : 4,
                "lg" : 2
              },
              "propertyValues" : {
                "cssClasses" : {
                  "type" : "constant",
                  "value" : ""
                },
                "hidden" : {
                  "type" : "constant",
                  "value" : false
                },
                "text" : {
                  "type" : "interpolation",
                  "value" : "<b> listApprobs </b>"
                },
                "alignment" : {
                  "type" : "constant",
                  "value" : "left"
                },
                "allowHTML" : {
                  "type" : "constant",
                  "value" : true
                },
                "labelHidden" : {
                  "type" : "constant",
                  "value" : true
                },
                "label" : {
                  "type" : "interpolation",
                  "value" : ""
                },
                "labelPosition" : {
                  "type" : "constant",
                  "value" : "top"
                },
                "labelWidth" : {
                  "type" : "constant",
                  "value" : 4
                }
              },
              "reference" : "046057f4-a73a-4b63-923e-b2d5f7d062ff",
              "hasValidationError" : false,
              "id" : "pbText"
            },
            {
              "type" : "component",
              "dimension" : {
                "xs" : 12,
                "sm" : 12,
                "md" : 2,
                "lg" : 3
              },
              "propertyValues" : {
                "cssClasses" : {
                  "type" : "constant",
                  "value" : ""
                },
                "hidden" : {
                  "type" : "constant",
                  "value" : false
                },
                "text" : {
                  "type" : "interpolation",
                  "value" : "<b>libNoeudApprob</b>"
                },
                "alignment" : {
                  "type" : "constant",
                  "value" : "left"
                },
                "allowHTML" : {
                  "type" : "constant",
                  "value" : true
                },
                "labelHidden" : {
                  "type" : "constant",
                  "value" : true
                },
                "label" : {
                  "type" : "interpolation",
                  "value" : ""
                },
                "labelPosition" : {
                  "type" : "constant",
                  "value" : "top"
                },
                "labelWidth" : {
                  "type" : "constant",
                  "value" : 4
                }
              },
              "reference" : "027125fe-44bb-49bc-af8f-6d25cb90e013",
              "hasValidationError" : false,
              "id" : "pbText"
            },
            {
              "type" : "component",
              "dimension" : {
                "xs" : 12,
                "sm" : 12,
                "md" : 2,
                "lg" : 3
              },
              "propertyValues" : {
                "cssClasses" : {
                  "type" : "constant",
                  "value" : ""
                },
                "hidden" : {
                  "type" : "constant",
                  "value" : false
                },
                "text" : {
                  "type" : "interpolation",
                  "value" : "<b>SGidSmarte</b>"
                },
                "alignment" : {
                  "type" : "constant",
                  "value" : "left"
                },
                "allowHTML" : {
                  "type" : "constant",
                  "value" : true
                },
                "labelHidden" : {
                  "type" : "constant",
                  "value" : true
                },
                "label" : {
                  "type" : "interpolation",
                  "value" : ""
                },
                "labelPosition" : {
                  "type" : "constant",
                  "value" : "top"
                },
                "labelWidth" : {
                  "type" : "constant",
                  "value" : 4
                }
              },
              "reference" : "30b8d603-0b28-4229-aacd-00280a69154e",
              "hasValidationError" : false,
              "id" : "pbText"
            }
          ]
        ]
      }
    ],
    [
      {
        "type" : "container",
        "dimension" : {
          "xs" : 12,
          "sm" : 12,
          "md" : 12,
          "lg" : 12
        },
        "propertyValues" : {
          "cssClasses" : {
            "type" : "constant",
            "value" : ""
          },
          "hidden" : {
            "type" : "constant",
            "value" : false
          },
          "repeatedCollection" : {
            "type" : "variable",
            "value" : "listApprobateurs"
          }
        },
        "reference" : "a8beb214-4c47-49e2-9d9d-03e758205ab9",
        "hasValidationError" : false,
        "id" : "pbContainer",
        "rows" : [
          [
            {
              "type" : "container",
              "dimension" : {
                "xs" : 12,
                "sm" : 12,
                "md" : 12,
                "lg" : 4
              },
              "propertyValues" : {
                "cssClasses" : {
                  "type" : "expression",
                  "value" : "$item.listApprobs.includes('UTILISATEUR INCONNU')== true ? \"red\" : \"\""
                },
                "hidden" : {
                  "type" : "constant",
                  "value" : false
                },
                "repeatedCollection" : {
                  "type" : "variable"
                }
              },
              "reference" : "e1c9b364-3e67-4a16-90b2-3c14818a740c",
              "hasValidationError" : false,
              "id" : "pbContainer",
              "rows" : [
                [
                  {
                    "type" : "component",
                    "dimension" : {
                      "xs" : 12,
                      "sm" : 12,
                      "md" : 2,
                      "lg" : 2
                    },
                    "propertyValues" : {
                      "cssClasses" : {
                        "type" : "constant",
                        "value" : ""
                      },
                      "hidden" : {
                        "type" : "constant",
                        "value" : false
                      },
                      "text" : {
                        "type" : "interpolation",
                        "value" : "$item.codeNoeudApprob"
                      },
                      "alignment" : {
                        "type" : "constant",
                        "value" : "left"
                      },
                      "allowHTML" : {
                        "type" : "constant",
                        "value" : true
                      },
                      "labelHidden" : {
                        "type" : "constant",
                        "value" : true
                      },
                      "label" : {
                        "type" : "interpolation",
                        "value" : ""
                      },
                      "labelPosition" : {
                        "type" : "constant",
                        "value" : "top"
                      },
                      "labelWidth" : {
                        "type" : "constant",
                        "value" : 4
                      }
                    },
                    "reference" : "6b964466-53e3-44d3-a996-ee2b9b4e087f",
                    "hasValidationError" : false,
                    "id" : "pbText"
                  },
                  {
                    "type" : "component",
                    "dimension" : {
                      "xs" : 12,
                      "sm" : 12,
                      "md" : 2,
                      "lg" : 2
                    },
                    "propertyValues" : {
                      "cssClasses" : {
                        "type" : "constant",
                        "value" : ""
                      },
                      "hidden" : {
                        "type" : "constant",
                        "value" : false
                      },
                      "text" : {
                        "type" : "interpolation",
                        "value" : "{{ $item.nomNoeudApprob }}"
                      },
                      "alignment" : {
                        "type" : "constant",
                        "value" : "left"
                      },
                      "allowHTML" : {
                        "type" : "constant",
                        "value" : true
                      },
                      "labelHidden" : {
                        "type" : "constant",
                        "value" : true
                      },
                      "label" : {
                        "type" : "interpolation",
                        "value" : ""
                      },
                      "labelPosition" : {
                        "type" : "constant",
                        "value" : "top"
                      },
                      "labelWidth" : {
                        "type" : "constant",
                        "value" : 4
                      }
                    },
                    "reference" : "0b1bdf95-c43a-4692-b9e0-b355d095f3d0",
                    "hasValidationError" : false,
                    "id" : "pbText"
                  },
                  {
                    "type" : "component",
                    "dimension" : {
                      "xs" : 12,
                      "sm" : 12,
                      "md" : 4,
                      "lg" : 2
                    },
                    "propertyValues" : {
                      "cssClasses" : {
                        "type" : "expression",
                        "value" : ""
                      },
                      "hidden" : {
                        "type" : "constant",
                        "value" : false
                      },
                      "text" : {
                        "type" : "interpolation",
                        "value" : "{{ $item.listApprobs}}"
                      },
                      "alignment" : {
                        "type" : "constant",
                        "value" : "left"
                      },
                      "allowHTML" : {
                        "type" : "constant",
                        "value" : true
                      },
                      "labelHidden" : {
                        "type" : "constant",
                        "value" : true
                      },
                      "label" : {
                        "type" : "interpolation",
                        "value" : ""
                      },
                      "labelPosition" : {
                        "type" : "constant",
                        "value" : "top"
                      },
                      "labelWidth" : {
                        "type" : "constant",
                        "value" : 4
                      }
                    },
                    "reference" : "4f3e59a0-0568-42a3-92d0-3da1350352c7",
                    "hasValidationError" : false,
                    "id" : "pbText"
                  },
                  {
                    "type" : "component",
                    "dimension" : {
                      "xs" : 12,
                      "sm" : 12,
                      "md" : 2,
                      "lg" : 3
                    },
                    "propertyValues" : {
                      "cssClasses" : {
                        "type" : "constant",
                        "value" : ""
                      },
                      "hidden" : {
                        "type" : "constant",
                        "value" : false
                      },
                      "text" : {
                        "type" : "interpolation",
                        "value" : "{{ $item.libNoeudApprob}}"
                      },
                      "alignment" : {
                        "type" : "constant",
                        "value" : "left"
                      },
                      "allowHTML" : {
                        "type" : "constant",
                        "value" : true
                      },
                      "labelHidden" : {
                        "type" : "constant",
                        "value" : true
                      },
                      "label" : {
                        "type" : "interpolation",
                        "value" : ""
                      },
                      "labelPosition" : {
                        "type" : "constant",
                        "value" : "top"
                      },
                      "labelWidth" : {
                        "type" : "constant",
                        "value" : 4
                      }
                    },
                    "reference" : "141ba3fe-59a3-48ad-994b-818763c27636",
                    "hasValidationError" : false,
                    "id" : "pbText"
                  },
                  {
                    "type" : "component",
                    "dimension" : {
                      "xs" : 12,
                      "sm" : 12,
                      "md" : 2,
                      "lg" : 3
                    },
                    "propertyValues" : {
                      "cssClasses" : {
                        "type" : "constant",
                        "value" : ""
                      },
                      "hidden" : {
                        "type" : "constant",
                        "value" : false
                      },
                      "text" : {
                        "type" : "interpolation",
                        "value" : "{{ $item.SGidSmarte}}"
                      },
                      "alignment" : {
                        "type" : "constant",
                        "value" : "left"
                      },
                      "allowHTML" : {
                        "type" : "constant",
                        "value" : true
                      },
                      "labelHidden" : {
                        "type" : "constant",
                        "value" : true
                      },
                      "label" : {
                        "type" : "interpolation",
                        "value" : ""
                      },
                      "labelPosition" : {
                        "type" : "constant",
                        "value" : "top"
                      },
                      "labelWidth" : {
                        "type" : "constant",
                        "value" : 4
                      }
                    },
                    "reference" : "abf378d9-40d7-460d-8122-6efb536ccb53",
                    "hasValidationError" : false,
                    "id" : "pbText"
                  }
                ]
              ]
            }
          ]
        ]
      }
    ],
    [
      {
        "type" : "component",
        "dimension" : {
          "xs" : 12,
          "sm" : 12,
          "md" : 12,
          "lg" : 12
        },
        "propertyValues" : {
          "cssClasses" : {
            "type" : "constant",
            "value" : ""
          },
          "hidden" : {
            "type" : "constant",
            "value" : false
          },
          "headers" : {
            "type" : "constant",
            "value" : [
              "nomNoeudApprob",
              "listApprobs",
              "codeNoeudApprob",
              "libNoeudApprob",
              "SGidSmarte"
            ]
          },
          "content" : {
            "type" : "expression",
            "value" : "listApprobateurs"
          },
          "columnsKey" : {
            "type" : "constant",
            "value" : [
              "nomNoeudApprob",
              "listApprobs",
              "codeNoeudApprob",
              "libNoeudApprob",
              "SGidSmarte"
            ]
          },
          "selectedRow" : {
            "type" : "variable"
          },
          "allowHTML" : {
            "type" : "constant",
            "value" : false
          },
          "striped" : {
            "type" : "constant",
            "value" : true
          },
          "condensed" : {
            "type" : "constant",
            "value" : false
          },
          "bordered" : {
            "type" : "constant",
            "value" : false
          }
        },
        "reference" : "abdb0c46-e546-482a-853a-528e5ec706ab",
        "hasValidationError" : false,
        "id" : "pbTable"
      }
    ]
  ],
  "assets" : [
    {
      "id" : "92ed1e60-37e7-4e84-ac36-c9a4e7625d1e",
      "name" : "localization.json",
      "type" : "json",
      "order" : 0,
      "external" : false
    },
    {
      "id" : "cc26a135-b7de-4223-a9c8-8d22a0516c91",
      "name" : "cssTest.css",
      "type" : "css",
      "order" : 1,
      "external" : false
    },
    {
      "id" : "636ebf24-85fc-414d-8f1e-4b30dcd848e4",
      "name" : "style.css",
      "type" : "css",
      "order" : 0,
      "external" : false
    }
  ],
  "inactiveAssets" : [ ],
  "variables" : {
    "listApprobateurs" : {
      "type" : "json",
      "value" : [
        "[\r",
        "    {\r",
        "        \"nomNoeudApprob\": \"PP-Nanterre\",\r",
        "        \"listApprobs\": \"UTILISATEUR INCONNU : sgidAAAA, Walter Bates (walter.bates)\",\r",
        "        \"codeNoeudApprob\": \"001\",\r",
        "        \"libNoeudApprob\": \"Site\",\r",
        "        \"SGidSmarte\": \"A01234\"\r",
        "    },\r",
        "    {\r",
        "        \"nomNoeudApprob\": \"PP IdF Ouest\",\r",
        "        \"listApprobs\": \"Giovanna Almeida (giovanna.almeida), Isabel Bleasdale (isabel.bleasdale)\",\r",
        "        \"codeNoeudApprob\": \"01\",\r",
        "        \"libNoeudApprob\": \"Secteur\",\r",
        "        \"SGidSmarte\": \"A01234\"\r",
        "    },\r",
        "    {\r",
        "        \"nomNoeudApprob\": \"PP IdF\",\r",
        "        \"listApprobs\": \"Daniela Angelo (daniela.angelo)\",\r",
        "        \"codeNoeudApprob\": \"1\",\r",
        "        \"libNoeudApprob\": \"Entit\\u00e9\",\r",
        "        \"SGidSmarte\": \"A01234\"\r",
        "    }\r",
        "]"
      ],
      "exposed" : false
    }
  },
  "hasValidationError" : false,
  "uuid" : "96c97b6b-8578-47f5-8914-3378a66d6b1d",
  "type" : "page",
  "description" : "Page generated with Bonita UI designer"
}