{
  "modelVersion" : "2.2",
  "previousArtifactVersion" : "2.0",
  "id" : "f1c2ef1c-1c08-49f3-890b-e70c861711d4",
  "name" : "ListeDemandeFmt",
  "lastUpdate" : 1671627910472,
  "rows" : [
    [
      {
        "type" : "container",
        "dimension" : {
          "xs" : 12,
          "sm" : 12,
          "md" : 12,
          "lg" : 12
        },
        "propertyValues" : {
          "cssClasses" : {
            "type" : "constant",
            "value" : ""
          },
          "hidden" : {
            "type" : "constant",
            "value" : false
          },
          "repeatedCollection" : {
            "type" : "variable"
          }
        },
        "reference" : "a4af7afb-6577-4efb-850e-99a90fc2e5ac",
        "hasValidationError" : false,
        "id" : "pbContainer",
        "rows" : [
          [
            {
              "type" : "component",
              "dimension" : {
                "xs" : 12,
                "sm" : 12,
                "md" : 12,
                "lg" : 12
              },
              "propertyValues" : {
                "cssClasses" : {
                  "type" : "constant",
                  "value" : ""
                },
                "hidden" : {
                  "type" : "constant",
                  "value" : false
                },
                "text" : {
                  "type" : "interpolation",
                  "value" : "Toutes les propositions"
                },
                "level" : {
                  "type" : "constant",
                  "value" : "Level 4"
                },
                "alignment" : {
                  "type" : "constant",
                  "value" : "left"
                }
              },
              "reference" : "4e3e6f1c-abd0-43d1-b7d3-3068f980bbbb",
              "hasValidationError" : false,
              "id" : "pbTitle"
            }
          ],
          [
            {
              "type" : "container",
              "dimension" : {
                "xs" : 12,
                "sm" : 12,
                "md" : 12,
                "lg" : 12
              },
              "propertyValues" : {
                "cssClasses" : {
                  "type" : "constant",
                  "value" : ""
                },
                "hidden" : {
                  "type" : "constant",
                  "value" : false
                },
                "repeatedCollection" : {
                  "type" : "variable"
                }
              },
              "reference" : "7eaeaef0-2730-4145-bdaa-708a323dd7bf",
              "hasValidationError" : false,
              "id" : "pbContainer",
              "rows" : [
                [
                  {
                    "type" : "component",
                    "dimension" : {
                      "xs" : 12,
                      "sm" : 12,
                      "md" : 4,
                      "lg" : 4
                    },
                    "propertyValues" : {
                      "cssClasses" : {
                        "type" : "constant",
                        "value" : ""
                      },
                      "hidden" : {
                        "type" : "constant",
                        "value" : false
                      },
                      "required" : {
                        "type" : "constant",
                        "value" : false
                      },
                      "minLength" : {
                        "type" : "constant",
                        "value" : ""
                      },
                      "maxLength" : {
                        "type" : "constant",
                        "value" : ""
                      },
                      "readOnly" : {
                        "type" : "constant",
                        "value" : false
                      },
                      "labelHidden" : {
                        "type" : "constant",
                        "value" : true
                      },
                      "label" : {
                        "type" : "interpolation",
                        "value" : "Default label"
                      },
                      "labelPosition" : {
                        "type" : "constant",
                        "value" : "top"
                      },
                      "labelWidth" : {
                        "type" : "constant",
                        "value" : 4
                      },
                      "placeholder" : {
                        "type" : "interpolation",
                        "value" : "Année de budget"
                      },
                      "value" : {
                        "type" : "variable",
                        "value" : "filters.year"
                      },
                      "type" : {
                        "type" : "constant",
                        "value" : "text"
                      },
                      "min" : {
                        "type" : "constant"
                      },
                      "max" : {
                        "type" : "constant"
                      },
                      "step" : {
                        "type" : "constant",
                        "value" : 1
                      }
                    },
                    "reference" : "9d1e8fc7-f4f0-4a5c-a6af-c31e5684388e",
                    "hasValidationError" : false,
                    "id" : "pbInput"
                  },
                  {
                    "type" : "component",
                    "dimension" : {
                      "xs" : 12,
                      "sm" : 12,
                      "md" : 4,
                      "lg" : 4
                    },
                    "propertyValues" : {
                      "cssClasses" : {
                        "type" : "constant",
                        "value" : ""
                      },
                      "hidden" : {
                        "type" : "constant",
                        "value" : false
                      },
                      "disabled" : {
                        "type" : "constant",
                        "value" : false
                      },
                      "required" : {
                        "type" : "constant",
                        "value" : false
                      },
                      "labelHidden" : {
                        "type" : "constant",
                        "value" : true
                      },
                      "label" : {
                        "type" : "interpolation",
                        "value" : "Select"
                      },
                      "labelPosition" : {
                        "type" : "constant",
                        "value" : "top"
                      },
                      "labelWidth" : {
                        "type" : "constant",
                        "value" : 4
                      },
                      "placeholder" : {
                        "type" : "interpolation",
                        "value" : "Type de proposition"
                      },
                      "availableValues" : {
                        "type" : "expression",
                        "value" : "typeDemande"
                      },
                      "displayedKey" : {
                        "type" : "constant"
                      },
                      "returnedKey" : {
                        "type" : "constant"
                      },
                      "value" : {
                        "type" : "variable",
                        "value" : "filters.type"
                      }
                    },
                    "reference" : "4b350874-8f20-4079-804d-0a0cfd627d11",
                    "hasValidationError" : false,
                    "id" : "pbSelect"
                  },
                  {
                    "type" : "component",
                    "dimension" : {
                      "xs" : 12,
                      "sm" : 12,
                      "md" : 4,
                      "lg" : 4
                    },
                    "propertyValues" : {
                      "cssClasses" : {
                        "type" : "constant",
                        "value" : ""
                      },
                      "hidden" : {
                        "type" : "constant",
                        "value" : false
                      },
                      "disabled" : {
                        "type" : "constant",
                        "value" : false
                      },
                      "required" : {
                        "type" : "constant",
                        "value" : false
                      },
                      "labelHidden" : {
                        "type" : "constant",
                        "value" : true
                      },
                      "label" : {
                        "type" : "interpolation",
                        "value" : "Select"
                      },
                      "labelPosition" : {
                        "type" : "constant",
                        "value" : "top"
                      },
                      "labelWidth" : {
                        "type" : "constant",
                        "value" : 4
                      },
                      "placeholder" : {
                        "type" : "interpolation",
                        "value" : "Statut"
                      },
                      "availableValues" : {
                        "type" : "constant",
                        "value" : [
                          "Draft",
                          "Rejected",
                          "Validated agency",
                          "Validated site",
                          "Validated sector",
                          "Validated region"
                        ]
                      },
                      "displayedKey" : {
                        "type" : "constant"
                      },
                      "returnedKey" : {
                        "type" : "constant"
                      },
                      "value" : {
                        "type" : "variable",
                        "value" : "filters.status"
                      }
                    },
                    "reference" : "e94fda11-7a22-4eb2-b2bb-ba179eabd32b",
                    "hasValidationError" : false,
                    "id" : "pbSelect"
                  }
                ],
                [
                  {
                    "type" : "component",
                    "dimension" : {
                      "xs" : 12,
                      "sm" : 12,
                      "md" : 3,
                      "lg" : 3
                    },
                    "propertyValues" : {
                      "cssClasses" : {
                        "type" : "constant",
                        "value" : ""
                      },
                      "hidden" : {
                        "type" : "constant",
                        "value" : false
                      },
                      "required" : {
                        "type" : "constant",
                        "value" : false
                      },
                      "minLength" : {
                        "type" : "constant",
                        "value" : ""
                      },
                      "maxLength" : {
                        "type" : "constant",
                        "value" : ""
                      },
                      "readOnly" : {
                        "type" : "constant",
                        "value" : false
                      },
                      "labelHidden" : {
                        "type" : "constant",
                        "value" : true
                      },
                      "label" : {
                        "type" : "interpolation",
                        "value" : "Default label"
                      },
                      "labelPosition" : {
                        "type" : "constant",
                        "value" : "top"
                      },
                      "labelWidth" : {
                        "type" : "constant",
                        "value" : 4
                      },
                      "placeholder" : {
                        "type" : "interpolation",
                        "value" : "Territoire"
                      },
                      "value" : {
                        "type" : "variable",
                        "value" : "filters.territoryCode"
                      },
                      "type" : {
                        "type" : "constant",
                        "value" : "text"
                      },
                      "min" : {
                        "type" : "constant"
                      },
                      "max" : {
                        "type" : "constant"
                      },
                      "step" : {
                        "type" : "constant",
                        "value" : 1
                      }
                    },
                    "reference" : "5cdd93ea-2fed-44b9-8378-f0e6232663a7",
                    "hasValidationError" : false,
                    "id" : "pbInput"
                  },
                  {
                    "type" : "component",
                    "dimension" : {
                      "xs" : 12,
                      "sm" : 12,
                      "md" : 3,
                      "lg" : 3
                    },
                    "propertyValues" : {
                      "cssClasses" : {
                        "type" : "constant",
                        "value" : ""
                      },
                      "hidden" : {
                        "type" : "constant",
                        "value" : false
                      },
                      "required" : {
                        "type" : "constant",
                        "value" : false
                      },
                      "minLength" : {
                        "type" : "constant",
                        "value" : ""
                      },
                      "maxLength" : {
                        "type" : "constant",
                        "value" : ""
                      },
                      "readOnly" : {
                        "type" : "constant",
                        "value" : false
                      },
                      "labelHidden" : {
                        "type" : "constant",
                        "value" : true
                      },
                      "label" : {
                        "type" : "interpolation",
                        "value" : "Default label"
                      },
                      "labelPosition" : {
                        "type" : "constant",
                        "value" : "top"
                      },
                      "labelWidth" : {
                        "type" : "constant",
                        "value" : 4
                      },
                      "placeholder" : {
                        "type" : "interpolation",
                        "value" : "Secteur"
                      },
                      "value" : {
                        "type" : "variable",
                        "value" : "filters.sectorCode"
                      },
                      "type" : {
                        "type" : "constant",
                        "value" : "text"
                      },
                      "min" : {
                        "type" : "constant"
                      },
                      "max" : {
                        "type" : "constant"
                      },
                      "step" : {
                        "type" : "constant",
                        "value" : 1
                      }
                    },
                    "reference" : "6e43ab11-f0b2-4e12-8bdc-576f18c0aae9",
                    "hasValidationError" : false,
                    "id" : "pbInput"
                  },
                  {
                    "type" : "component",
                    "dimension" : {
                      "xs" : 12,
                      "sm" : 12,
                      "md" : 3,
                      "lg" : 3
                    },
                    "propertyValues" : {
                      "cssClasses" : {
                        "type" : "constant",
                        "value" : ""
                      },
                      "hidden" : {
                        "type" : "constant",
                        "value" : false
                      },
                      "required" : {
                        "type" : "constant",
                        "value" : false
                      },
                      "minLength" : {
                        "type" : "constant",
                        "value" : ""
                      },
                      "maxLength" : {
                        "type" : "constant",
                        "value" : ""
                      },
                      "readOnly" : {
                        "type" : "constant",
                        "value" : false
                      },
                      "labelHidden" : {
                        "type" : "constant",
                        "value" : true
                      },
                      "label" : {
                        "type" : "interpolation",
                        "value" : "Default label"
                      },
                      "labelPosition" : {
                        "type" : "constant",
                        "value" : "top"
                      },
                      "labelWidth" : {
                        "type" : "constant",
                        "value" : 4
                      },
                      "placeholder" : {
                        "type" : "interpolation",
                        "value" : "Site"
                      },
                      "value" : {
                        "type" : "variable",
                        "value" : "filters.siteCode"
                      },
                      "type" : {
                        "type" : "constant",
                        "value" : "text"
                      },
                      "min" : {
                        "type" : "constant"
                      },
                      "max" : {
                        "type" : "constant"
                      },
                      "step" : {
                        "type" : "constant",
                        "value" : 1
                      }
                    },
                    "reference" : "ba82e0b2-d4ed-4b43-9d3f-91575f85a380",
                    "hasValidationError" : false,
                    "id" : "pbInput"
                  },
                  {
                    "type" : "component",
                    "dimension" : {
                      "xs" : 12,
                      "sm" : 12,
                      "md" : 3,
                      "lg" : 3
                    },
                    "propertyValues" : {
                      "cssClasses" : {
                        "type" : "constant",
                        "value" : ""
                      },
                      "hidden" : {
                        "type" : "constant",
                        "value" : false
                      },
                      "required" : {
                        "type" : "constant",
                        "value" : false
                      },
                      "minLength" : {
                        "type" : "constant",
                        "value" : ""
                      },
                      "maxLength" : {
                        "type" : "constant",
                        "value" : ""
                      },
                      "readOnly" : {
                        "type" : "constant",
                        "value" : false
                      },
                      "labelHidden" : {
                        "type" : "constant",
                        "value" : true
                      },
                      "label" : {
                        "type" : "interpolation",
                        "value" : "Default label"
                      },
                      "labelPosition" : {
                        "type" : "constant",
                        "value" : "top"
                      },
                      "labelWidth" : {
                        "type" : "constant",
                        "value" : 4
                      },
                      "placeholder" : {
                        "type" : "interpolation",
                        "value" : "Agence"
                      },
                      "value" : {
                        "type" : "variable",
                        "value" : "filters.agencyCode"
                      },
                      "type" : {
                        "type" : "constant",
                        "value" : "text"
                      },
                      "min" : {
                        "type" : "constant"
                      },
                      "max" : {
                        "type" : "constant"
                      },
                      "step" : {
                        "type" : "constant",
                        "value" : 1
                      }
                    },
                    "reference" : "fe3bfd6d-dd1c-452e-b986-8a363383d5f5",
                    "hasValidationError" : false,
                    "id" : "pbInput"
                  }
                ]
              ]
            }
          ],
          [
            {
              "type" : "container",
              "dimension" : {
                "xs" : 12,
                "sm" : 12,
                "md" : 12,
                "lg" : 12
              },
              "propertyValues" : {
                "cssClasses" : {
                  "type" : "constant",
                  "value" : ""
                },
                "hidden" : {
                  "type" : "constant",
                  "value" : false
                },
                "repeatedCollection" : {
                  "type" : "variable"
                }
              },
              "reference" : "b3d76acc-4ce3-44b8-b2e8-977a0d09e7cc",
              "hasValidationError" : false,
              "id" : "pbContainer",
              "rows" : [
                [
                  {
                    "type" : "component",
                    "dimension" : {
                      "xs" : 12,
                      "sm" : 12,
                      "md" : 12,
                      "lg" : 12
                    },
                    "propertyValues" : {
                      "cssClasses" : {
                        "type" : "constant",
                        "value" : ""
                      },
                      "hidden" : {
                        "type" : "constant",
                        "value" : false
                      },
                      "headers" : {
                        "type" : "constant",
                        "value" : [
                          "Id",
                          "Année",
                          "Teritoire",
                          "Secteur",
                          "Site",
                          "Agence",
                          "Type",
                          "Initiateur",
                          "Statut"
                        ]
                      },
                      "type" : {
                        "type" : "constant",
                        "value" : "Bonita API"
                      },
                      "apiUrl" : {
                        "type" : "expression",
                        "value" : "urlListProposition"
                      },
                      "params" : {
                        "type" : "constant"
                      },
                      "content" : {
                        "type" : "constant"
                      },
                      "columnsKey" : {
                        "type" : "constant",
                        "value" : [
                          "id",
                          "year",
                          "territory",
                          "sector",
                          "site",
                          "agency",
                          "type",
                          "requester",
                          "status"
                        ]
                      },
                      "sortColumns" : {
                        "type" : "constant",
                        "value" : [ ]
                      },
                      "selectedRow" : {
                        "type" : "variable"
                      },
                      "pageSize" : {
                        "type" : "constant",
                        "value" : 10
                      },
                      "filter" : {
                        "type" : "constant"
                      },
                      "allowHTML" : {
                        "type" : "constant",
                        "value" : false
                      },
                      "striped" : {
                        "type" : "constant",
                        "value" : true
                      },
                      "condensed" : {
                        "type" : "constant",
                        "value" : false
                      },
                      "bordered" : {
                        "type" : "constant",
                        "value" : false
                      }
                    },
                    "reference" : "9b311bce-c0e2-4f64-b6c3-a7638fb785a2",
                    "hasValidationError" : false,
                    "id" : "pbDataTable"
                  }
                ]
              ]
            }
          ],
          [
            {
              "type" : "component",
              "dimension" : {
                "xs" : 12,
                "sm" : 12,
                "md" : 12,
                "lg" : 12
              },
              "propertyValues" : {
                "cssClasses" : {
                  "type" : "constant",
                  "value" : ""
                },
                "hidden" : {
                  "type" : "constant",
                  "value" : true
                },
                "text" : {
                  "type" : "interpolation",
                  "value" : "<pre>url: {{urlListProposition}}\n<br />\nfilters: {{filters | json}}\n</pre>"
                },
                "alignment" : {
                  "type" : "constant",
                  "value" : "left"
                },
                "allowHTML" : {
                  "type" : "constant",
                  "value" : true
                },
                "labelHidden" : {
                  "type" : "constant",
                  "value" : true
                },
                "label" : {
                  "type" : "interpolation",
                  "value" : ""
                },
                "labelPosition" : {
                  "type" : "constant",
                  "value" : "top"
                },
                "labelWidth" : {
                  "type" : "constant",
                  "value" : 4
                }
              },
              "reference" : "4c86663e-1916-48b7-8467-ea912eca691b",
              "hasValidationError" : false,
              "id" : "pbText"
            }
          ]
        ]
      }
    ]
  ],
  "assets" : [ ],
  "inactiveAssets" : [ ],
  "variables" : {
    "urlListProposition" : {
      "type" : "expression",
      "value" : [
        "var url=\"\";",
        "if ($data.profile!=undefined){",
        "    url += \"../API/extension/listBudgetProposition?role=\" + $data.profile;",
        "    if ($data.filters.year!==undefined && $data.filters.year.length==4){",
        "        url += \"&year=\" + $data.filters.year;",
        "    }",
        "    if ($data.filters.territoryCode!==undefined && $data.filters.territoryCode.length>2){",
        "        url += \"&territoryCode=\" + $data.filters.territoryCode;",
        "    }",
        "    ",
        "    if ($data.filters.sectorCode!==undefined && $data.filters.sectorCode.length>2){",
        "        url += \"&sectorCode=\" + $data.filters.sectorCode;",
        "    }",
        "    if ($data.filters.siteCode!==undefined && $data.filters.siteCode.length>2){",
        "        url += \"&siteCode=\" + $data.filters.siteCode;",
        "    }",
        "    if ($data.filters.agencyCode!==undefined && $data.filters.agencyCode.length>2){",
        "        url += \"&agencyCode=\" + $data.filters.agencyCode;",
        "    }",
        "    if ($data.filters.status!==undefined){",
        "        url += \"&status=\" + $data.filters.status;",
        "    }",
        "    if ($data.filters.type!==undefined){",
        "        url += \"&type=\" + $data.filters.type;",
        "    }",
        "}",
        "return url;"
      ],
      "exposed" : false
    },
    "profile" : {
      "type" : "constant",
      "value" : [
        "User"
      ],
      "exposed" : false
    },
    "filters" : {
      "type" : "json",
      "value" : [
        "{",
        "    \"territoryCode\":\"\",",
        "    \"sectorCode\":\"\",",
        "    \"siteCode\":\"\",",
        "    \"agencyCode\":\"\",",
        "    \"year\":\"\",",
        "    \"type\":\"\",",
        "    \"status\":\"\"",
        "}"
      ],
      "exposed" : false
    },
    "typeDemande" : {
      "type" : "url",
      "value" : [
        "../API/extension/listeTypeParameter?parameterName=motifsProposition"
      ],
      "exposed" : false
    }
  },
  "hasValidationError" : false,
  "type" : "fragment"
}